rwanda/__init__.py
rwanda/local.py
rwanda/locations/__init__.py
rwanda/locations/locations.json
rwanda-0.2.2.dist-info/LICENSE
rwanda-0.2.2.dist-info/METADATA
rwanda-0.2.2.dist-info/WHEEL
rwanda-0.2.2.dist-info/RECORD
